[
  {
    "categories": [],
    "created_at": "2020-01-05 13:42:19.104863",
    "icon_url": "https://assets.chucknorris.host/img/avatar/chuck-norris.png",
    "id": "VU5friiSScSKok3T_VTwjg",
    "updated_at": "2020-01-05 13:42:19.104863",
    "url": "https://api.chucknorris.io/jokes/VU5friiSScSKok3T_VTwjg",
    "value": "God used to make frequent trips to earth to talk to various people. Upon seeing Chuck Norris' manly good looks God vanquished himself to heaven, never to be seen again out of embarassment of his own self image. It's rumored Chuck is currently God's personal fitness trainer."
  },
  {
    "categories": [],
    "created_at": "2020-01-05 13:42:19.897976",
    "icon_url": "https://assets.chucknorris.host/img/avatar/chuck-norris.png",
    "id": "FkULWBTyQreefpAgiv88FA",
    "updated_at": "2020-01-05 13:42:19.897976",
    "url": "https://api.chucknorris.io/jokes/FkULWBTyQreefpAgiv88FA",
    "value": "During karate training Chuck Norris prefers to use an elephant scrotum as a speed bag."
  },
  {
    "categories": [],
    "created_at": "2020-01-05 13:42:20.262289",
    "icon_url": "https://assets.chucknorris.host/img/avatar/chuck-norris.png",
    "id": "JtZFGZbTRLOT-1Vww58wdQ",
    "updated_at": "2020-01-05 13:42:20.262289",
    "url": "https://api.chucknorris.io/jokes/JtZFGZbTRLOT-1Vww58wdQ",
    "value": "There is a light at the end of every tunnel, just pray it's not the frieght train called Chuck Norris."
  },
  {
    "categories": [],
    "created_at": "2020-01-05 13:42:20.262289",
    "icon_url": "https://assets.chucknorris.host/img/avatar/chuck-norris.png",
    "id": "NS48Bp8XQUSad3FheB8RiQ",
    "updated_at": "2020-01-05 13:42:20.262289",
    "url": "https://api.chucknorris.io/jokes/NS48Bp8XQUSad3FheB8RiQ",
    "value": "By twerking daily, Miley Cyrus is in training to build up her ass & snatch muscles enough to be the first woman in history to satisfy Chuck Norris in less than 5 hours by his pile driving rigid tool."
  },
  {
    "categories": [],
    "created_at": "2020-01-05 13:42:20.262289",
    "icon_url": "https://assets.chucknorris.host/img/avatar/chuck-norris.png",
    "id": "cak4t8GvSomqpGsoUgOGng",
    "updated_at": "2020-01-05 13:42:20.262289",
    "url": "https://api.chucknorris.io/jokes/cak4t8GvSomqpGsoUgOGng",
    "value": "Chuck Norris usually prefers to travel on the OUTSIDE of taxis, trains and commercial aircraft."
  },
  {
    "categories": [],
    "created_at": "2020-01-05 13:42:20.841843",
    "icon_url": "https://assets.chucknorris.host/img/avatar/chuck-norris.png",
    "id": "36mdZ_iDRRaU9iOB3IdAig",
    "updated_at": "2020-01-05 13:42:20.841843",
    "url": "https://api.chucknorris.io/jokes/36mdZ_iDRRaU9iOB3IdAig",
    "value": "Chuck Norris was hit by a train and the train was found 3 days later beyond recognition"
  },
  {
    "categories": [],
    "created_at": "2020-01-05 13:42:20.841843",
    "icon_url": "https://assets.chucknorris.host/img/avatar/chuck-norris.png",
    "id": "HQNc1r1dQPGRzue_yWSvaw",
    "updated_at": "2020-01-05 13:42:20.841843",
    "url": "https://api.chucknorris.io/jokes/HQNc1r1dQPGRzue_yWSvaw",
    "value": "Chuck Norris can do donuts in a steam train"
  },
  {
    "categories": [],
    "created_at": "2020-01-05 13:42:20.841843",
    "icon_url": "https://assets.chucknorris.host/img/avatar/chuck-norris.png",
    "id": "iCf7k3jURCy-CODRE0ouYQ",
    "updated_at": "2020-01-05 13:42:20.841843",
    "url": "https://api.chucknorris.io/jokes/iCf7k3jURCy-CODRE0ouYQ",
    "value": "Chuck Norris began weight training at age 3. He bench-pressed a 747 ten times."
  },
  {
    "categories": [],
    "created_at": "2020-01-05 13:42:21.179347",
    "icon_url": "https://assets.chucknorris.host/img/avatar/chuck-norris.png",
    "id": "99uYVWvCScmdIz0LDIXtDQ",
    "updated_at": "2020-01-05 13:42:21.179347",
    "url": "https://api.chucknorris.io/jokes/99uYVWvCScmdIz0LDIXtDQ",
    "value": "Chuck Norris relaxes in his acid bath to the soothing strains of Norwegian black metal."
  },
  {
    "categories": [],
    "created_at": "2020-01-05 13:42:21.179347",
    "icon_url": "https://assets.chucknorris.host/img/avatar/chuck-norris.png",
    "id": "AZ-bLagjQUKs-UFbGRTCHQ",
    "updated_at": "2020-01-05 13:42:21.179347",
    "url": "https://api.chucknorris.io/jokes/AZ-bLagjQUKs-UFbGRTCHQ",
    "value": "Chuck Norris can parallel park a freight train"
  },
  {
    "categories": [],
    "created_at": "2020-01-05 13:42:21.455187",
    "icon_url": "https://assets.chucknorris.host/img/avatar/chuck-norris.png",
    "id": "7ITtHdSCRNCssA0OwLDtmg",
    "updated_at": "2020-01-05 13:42:21.455187",
    "url": "https://api.chucknorris.io/jokes/7ITtHdSCRNCssA0OwLDtmg",
    "value": "Chuck Norris wields a freight train like nunchucks."
  },
  {
    "categories": [],
    "created_at": "2020-01-05 13:42:22.089095",
    "icon_url": "https://assets.chucknorris.host/img/avatar/chuck-norris.png",
    "id": "pCskm9xXSMOJ0C5--iwCAw",
    "updated_at": "2020-01-05 13:42:22.089095",
    "url": "https://api.chucknorris.io/jokes/pCskm9xXSMOJ0C5--iwCAw",
    "value": "Once, when crossing a RR track while riding his horse, Chuck Norris was struck by an Amtrak train. He was the only survivor."
  },
  {
    "categories": [],
    "created_at": "2020-01-05 13:42:22.701402",
    "icon_url": "https://assets.chucknorris.host/img/avatar/chuck-norris.png",
    "id": "UDIEYf2rQ42to8tMf2L0QQ",
    "updated_at": "2020-01-05 13:42:22.701402",
    "url": "https://api.chucknorris.io/jokes/UDIEYf2rQ42to8tMf2L0QQ",
    "value": "Chuck Norris once hijacked a frieght train and drove it to a Home Depot."
  },
  {
    "categories": [],
    "created_at": "2020-01-05 13:42:22.980058",
    "icon_url": "https://assets.chucknorris.host/img/avatar/chuck-norris.png",
    "id": "dn8JnNfwSh-uMxx34lVjjQ",
    "updated_at": "2020-01-05 13:42:22.980058",
    "url": "https://api.chucknorris.io/jokes/dn8JnNfwSh-uMxx34lVjjQ",
    "value": "Chuck Norris can drive a frieght train, trim his toenails and butcher a steer at the same time time."
  },
  {
    "categories": [],
    "created_at": "2020-01-05 13:42:23.240175",
    "icon_url": "https://assets.chucknorris.host/img/avatar/chuck-norris.png",
    "id": "IuWpcTlESJS_MeltxLr-wA",
    "updated_at": "2020-01-05 13:42:23.240175",
    "url": "https://api.chucknorris.io/jokes/IuWpcTlESJS_MeltxLr-wA",
    "value": "Chuck Norris can get free internet access, text messages and smart phone app functionality from train station pay phones."
  },
  {
    "categories": [],
    "created_at": "2020-01-05 13:42:23.880601",
    "icon_url": "https://assets.chucknorris.host/img/avatar/chuck-norris.png",
    "id": "Obi8Vp_uRXqrjmMgjrCPaw",
    "updated_at": "2020-01-05 13:42:23.880601",
    "url": "https://api.chucknorris.io/jokes/Obi8Vp_uRXqrjmMgjrCPaw",
    "value": "Gregg Valentino is known to have the biggest biceps on the planet. That's because he once accidentally dropped a weight on Chuck Norris foot while training in the gym with Chuck. That action Caused Chuck's reflex's to hammer-kick Valentino in each bicep. Now even Arnold is amazed at Valentino's giant swollen biceps."
  },
  {
    "categories": [],
    "created_at": "2020-01-05 13:42:24.142371",
    "icon_url": "https://assets.chucknorris.host/img/avatar/chuck-norris.png",
    "id": "ojt1AycKTRKQYP5XcMja-Q",
    "updated_at": "2020-01-05 13:42:24.142371",
    "url": "https://api.chucknorris.io/jokes/ojt1AycKTRKQYP5XcMja-Q",
    "value": "Chuck Norris doesn't bench press weight sets, he bench presses FREIGHT TRAINS!"
  },
  {
    "categories": [],
    "created_at": "2020-01-05 13:42:24.142371",
    "icon_url": "https://assets.chucknorris.host/img/avatar/chuck-norris.png",
    "id": "V7HGE2EuSf2slsf1pf6J1w",
    "updated_at": "2020-01-05 13:42:24.142371",
    "url": "https://api.chucknorris.io/jokes/V7HGE2EuSf2slsf1pf6J1w",
    "value": "After the start of the race, Chuck Norris took a two day vacation in Italy, eviscerated a Yeti in Switzerland, then won the Tour de France by riding backwards on a tricycle while potty training a wolverine."
  },
  {
    "categories": [],
    "created_at": "2020-01-05 13:42:24.40636",
    "icon_url": "https://assets.chucknorris.host/img/avatar/chuck-norris.png",
    "id": "qtQw_2q3QiWOp4FuXiiMlA",
    "updated_at": "2020-01-05 13:42:24.40636",
    "url": "https://api.chucknorris.io/jokes/qtQw_2q3QiWOp4FuXiiMlA",
    "value": "Chuck Norris can drive a freight train on a dirt road"
  },
  {
    "categories": [],
    "created_at": "2020-01-05 13:42:24.40636",
    "icon_url": "https://assets.chucknorris.host/img/avatar/chuck-norris.png",
    "id": "qa28q3tLRfiQueljgBm5Cw",
    "updated_at": "2020-01-05 13:42:24.40636",
    "url": "https://api.chucknorris.io/jokes/qa28q3tLRfiQueljgBm5Cw",
    "value": "Chuck Norris personally trained his pet canary for a daily early morning free flight excercise in the great outdoors. It usually returns for breakfast carrying a dead peregrine falcon in it's beak."
  },
  {
    "categories": [],
    "created_at": "2020-01-05 13:42:25.099703",
    "icon_url": "https://assets.chucknorris.host/img/avatar/chuck-norris.png",
    "id": "iTACqUclRay-Vo6msppPMw",
    "updated_at": "2020-01-05 13:42:25.099703",
    "url": "https://api.chucknorris.io/jokes/iTACqUclRay-Vo6msppPMw",
    "value": "Chuck Norris once played chicken with a train in an underground tunnel and won."
  },
  {
    "categories": [],
    "created_at": "2020-01-05 13:42:25.099703",
    "icon_url": "https://assets.chucknorris.host/img/avatar/chuck-norris.png",
    "id": "XvhvQJ7JRhG_uSo7-bXLdA",
    "updated_at": "2020-01-05 13:42:25.099703",
    "url": "https://api.chucknorris.io/jokes/XvhvQJ7JRhG_uSo7-bXLdA",
    "value": "Chuck Norris was once caught without a ticket on the train. The inspector was fined $110."
  },
  {
    "categories": [],
    "created_at": "2020-01-05 13:42:25.628594",
    "icon_url": "https://assets.chucknorris.host/img/avatar/chuck-norris.png",
    "id": "TfQL2xGoSXOi6KRmQrww9g",
    "updated_at": "2020-01-05 13:42:25.628594",
    "url": "https://api.chucknorris.io/jokes/TfQL2xGoSXOi6KRmQrww9g",
    "value": "When Chuck Norris was a year old, other kids his age were eating strained peas for dinner. Chuck would have a steak, medium rare. And a baked potato."
  },
  {
    "categories": [],
    "created_at": "2020-01-05 13:42:25.628594",
    "icon_url": "https://assets.chucknorris.host/img/avatar/chuck-norris.png",
    "id": "0MQbfP3PTBC2TvsL_C0w4A",
    "updated_at": "2020-01-05 13:42:25.628594",
    "url": "https://api.chucknorris.io/jokes/0MQbfP3PTBC2TvsL_C0w4A",
    "value": "Little known fact: Chuck Norris is rumored to have been the original choice to play evil Cobra Kai sensei John Kreese in The Karate Kid. Presumably he turned the role down because, realistically, no student trained by Chuck Norris could ever possibly lose a match."
  },
  {
    "categories": [],
    "created_at": "2020-01-05 13:42:25.905626",
    "icon_url": "https://assets.chucknorris.host/img/avatar/chuck-norris.png",
    "id": "YmIjTK1dS2WN5Tdxs74B2Q",
    "updated_at": "2020-01-05 13:42:25.905626",
    "url": "https://api.chucknorris.io/jokes/YmIjTK1dS2WN5Tdxs74B2Q",
    "value": "A man woke in Intensive Care with severe injuries and no memory of what happened. An investigation determined he was hit by either a freight train or by Chuck Norris."
  },
  {
    "categories": [],
    "created_at": "2020-01-05 13:42:26.194739",
    "icon_url": "https://assets.chucknorris.host/img/avatar/chuck-norris.png",
    "id": "t1HQRTDFRKG0yKzXf_4NnA",
    "updated_at": "2020-01-05 13:42:26.194739",
    "url": "https://api.chucknorris.io/jokes/t1HQRTDFRKG0yKzXf_4NnA",
    "value": "Following a recent kickboxing training mishap,Chuck Norris no longer has a shadow."
  },
  {
    "categories": [],
    "created_at": "2020-01-05 13:42:26.447675",
    "icon_url": "https://assets.chucknorris.host/img/avatar/chuck-norris.png",
    "id": "RtqvU-4UR12whu1GrNVEWg",
    "updated_at": "2020-01-05 13:42:26.447675",
    "url": "https://api.chucknorris.io/jokes/RtqvU-4UR12whu1GrNVEWg",
    "value": "Chuck Norris house trained his dog by 1 roundhouse kick to the face."
  },
  {
    "categories": [],
    "created_at": "2020-01-05 13:42:26.447675",
    "icon_url": "https://assets.chucknorris.host/img/avatar/chuck-norris.png",
    "id": "q_2TfZxJT3ubBKw_CZGAiw",
    "updated_at": "2020-01-05 13:42:26.447675",
    "url": "https://api.chucknorris.io/jokes/q_2TfZxJT3ubBKw_CZGAiw",
    "value": "Chuck Norris is Bruce Lee's trainer"
  },
  {
    "categories": [],
    "created_at": "2020-01-05 13:42:26.766831",
    "icon_url": "https://assets.chucknorris.host/img/avatar/chuck-norris.png",
    "id": "wi5BbveIRaG5jqwev764sw",
    "updated_at": "2020-01-05 13:42:26.766831",
    "url": "https://api.chucknorris.io/jokes/wi5BbveIRaG5jqwev764sw",
    "value": "Chuck Norris played chicken with a train...and won."
  },
  {
    "categories": [],
    "created_at": "2020-01-05 13:42:26.766831",
    "icon_url": "https://assets.chucknorris.host/img/avatar/chuck-norris.png",
    "id": "-Z5FIMGTSmGStr-gkend8w",
    "updated_at": "2020-01-05 13:42:26.766831",
    "url": "https://api.chucknorris.io/jokes/-Z5FIMGTSmGStr-gkend8w",
    "value": "When Chuck Norris was 5, he went to the Mall to see Santa. Santa asked \"what would you like little boy, a train set? A bike? Chuck replied \"no Santa, I want a rocket launcher\"."
  },
  {
    "categories": [],
    "created_at": "2020-01-05 13:42:27.496799",
    "icon_url": "https://assets.chucknorris.host/img/avatar/chuck-norris.png",
    "id": "a-Qza8aSRmaiITN8X3UeIQ",
    "updated_at": "2020-01-05 13:42:27.496799",
    "url": "https://api.chucknorris.io/jokes/a-Qza8aSRmaiITN8X3UeIQ",
    "value": "Chuck Norris' jock strap has 2 bag restraint holders."
  },
  {
    "categories": [],
    "created_at": "2020-01-05 13:42:27.496799",
    "icon_url": "https://assets.chucknorris.host/img/avatar/chuck-norris.png",
    "id": "1Ur8IM8PT7aza2iP6ma-FQ",
    "updated_at": "2020-01-05 13:42:27.496799",
    "url": "https://api.chucknorris.io/jokes/1Ur8IM8PT7aza2iP6ma-FQ",
    "value": "Human beings are roughly 60 percent water. Chuck Norris is roughly 80 percent whiskey, and the other 20 percent is barely restrained fury."
  },
  {
    "categories": [],
    "created_at": "2020-01-05 13:42:28.420821",
    "icon_url": "https://assets.chucknorris.host/img/avatar/chuck-norris.png",
    "id": "rqk9BuQLSx2ltHgvO7JqSg",
    "updated_at": "2020-01-05 13:42:28.420821",
    "url": "https://api.chucknorris.io/jokes/rqk9BuQLSx2ltHgvO7JqSg",
    "value": "Chuck Norris trained his pet mountain lions to nurse baby sheep and later fed them back to the mountain lions thus perpetuating mountain lion existence."
  },
  {
    "categories": [],
    "created_at": "2020-01-05 13:42:28.984661",
    "icon_url": "https://assets.chucknorris.host/img/avatar/chuck-norris.png",
    "id": "FIPHbmzvThGAWr2V6BuqLg",
    "updated_at": "2020-01-05 13:42:28.984661",
    "url": "https://api.chucknorris.io/jokes/FIPHbmzvThGAWr2V6BuqLg",
    "value": "Chuck Norris is so much trained in military tacticts 'that' once he killed an terrorist in afghanistan through bluetooth"
  },
  {
    "categories": [],
    "created_at": "2020-01-05 13:42:30.480041",
    "icon_url": "https://assets.chucknorris.host/img/avatar/chuck-norris.png",
    "id": "lP6V4K5cT0CM8RXH1MqESA",
    "updated_at": "2020-01-05 13:42:30.480041",
    "url": "https://api.chucknorris.io/jokes/lP6V4K5cT0CM8RXH1MqESA",
    "value": "Chuck Norris measurments are 10000-9000-30000000000000 the bottom piece is more bigger because he is best trained foot fighter(roundhousekick)"
  },
  {
    "categories": [],
    "created_at": "2020-01-05 13:42:30.480041",
    "icon_url": "https://assets.chucknorris.host/img/avatar/chuck-norris.png",
    "id": "kSvq4aCoS5SYSuVrNi1DHg",
    "updated_at": "2020-01-05 13:42:30.480041",
    "url": "https://api.chucknorris.io/jokes/kSvq4aCoS5SYSuVrNi1DHg",
    "value": "Chuck Norris can catch a train, i feel sorry for the person who has to throw it to him."
  },
  {
    "categories": [
      "test"
    ],
    "created_at": "2020-01-05 13:42:30.480041",
    "icon_url": "https://assets.chucknorris.host/img/avatar/chuck-norris.png",
    "id": "test_03",
    "updated_at": "2020-01-05 13:42:30.480041",
    "url": "https://api.chucknorris.io/jokes/kSvq4aCoS5SYSuVrNi1DHg",
    "value": "This is just a test for CREATE"
  },
  {
    "categories": [
      "test"
    ],
    "created_at": "2020-01-05 13:42:30.480041",
    "icon_url": "https://assets.chucknorris.host/img/avatar/chuck-norris.png",
    "id": "test_04",
    "updated_at": "2020-01-05 13:42:30.480041",
    "url": "https://api.chucknorris.io/jokes/kSvq4aCoS5SYSuVrNi1DHg",
    "value": "This is just a test for CREATE"
  }
]